kpi_evaluator/__init__.py
kpi_evaluator/evaluator.py
kpi_evaluator-0.3.0.dist-info/METADATA
kpi_evaluator-0.3.0.dist-info/WHEEL
kpi_evaluator-0.3.0.dist-info/top_level.txt
kpi_evaluator-0.3.0.dist-info/RECORD
