Metadata-Version: 2.1
Name: kpi-evaluator
Version: 0.3.0
Summary: Thư viện đánh giá KPI nhân viên bằng AI
Home-page: https://github.com/dsphanduc
Author: Phan Danh Đức
Author-email: phanduc.ds@gmail.com
Classifier: Programming Language :: Python :: 3
Classifier: License :: OSI Approved :: MIT License
Requires-Python: >=3.6
Requires-Dist: ollama
